lumikko/__init__.py
lumikko/__main__.py
lumikko/cli.py
lumikko/lumikko.py
lumikko/tree_shape.py
lumikko-2023.10.22.dist-info/LICENSE
lumikko-2023.10.22.dist-info/METADATA
lumikko-2023.10.22.dist-info/WHEEL
lumikko-2023.10.22.dist-info/entry_points.txt
lumikko-2023.10.22.dist-info/top_level.txt
lumikko-2023.10.22.dist-info/RECORD
