Metadata-Version: 2.1
Name: lumikko
Version: 2023.10.22
Summary: For now a lumikko (Finnish for wiesel), later maybe feed back changes upstream towards a lisko.
Author-email: Stefan Hagen <stefan@hagen.link>
Maintainer-email: Stefan Hagen <stefan@hagen.link>
Project-URL: Homepage, https://git.sr.ht/~sthagen/lumikko
Project-URL: Bug-Tracker, https://todo.sr.ht/~sthagen/lumikko
Project-URL: Documentation, https://codes.dilettant.life/docs/lumikko
Project-URL: Source-Code, https://git.sr.ht/~sthagen/lumikko
Project-URL: Test-Coverage, https://codes.dilettant.life/coverage/lumikko
Keywords: developer-tools,sloc,taxonomies
Classifier: Development Status :: 3 - Alpha
Classifier: Intended Audience :: Developers
Classifier: License :: OSI Approved :: MIT License
Classifier: Programming Language :: Python :: 3.10
Classifier: Programming Language :: Python :: 3.11
Classifier: Programming Language :: Python :: 3.12
Classifier: Programming Language :: Python :: 3.9
Requires-Python: >=3.9
License-File: LICENSE
Requires-Dist: GitPython >=3.1.40
Requires-Dist: markdown >=3.4.1
Provides-Extra: dev
Requires-Dist: black ; extra == 'dev'
Requires-Dist: coverage ; extra == 'dev'
Requires-Dist: hypothesis ; extra == 'dev'
Requires-Dist: mypy ; extra == 'dev'
Requires-Dist: pytest ; extra == 'dev'
Requires-Dist: pytest-cov ; extra == 'dev'
Requires-Dist: pytest-flake8 ; extra == 'dev'
Requires-Dist: ruff ; extra == 'dev'
